gnx/core/__init__.py
gnx/core/config.py
gnx/core/graph.py
gnx/datasource/__init__.py
gnx/nn/__init__.py
gnx/util/fs.py
gnx/util/trainer.py
gnx-0.0.1.dist-info/METADATA
gnx-0.0.1.dist-info/WHEEL
gnx-0.0.1.dist-info/top_level.txt
gnx-0.0.1.dist-info/RECORD
