Metadata-Version: 2.4
Name: gnx
Version: 0.0.1
Summary: Add your description here
Requires-Python: >=3.13
Requires-Dist: flax>=0.12.0
